<?xml version="1.0" encoding="utf-8" ?>
<Defs>

  <MentalStateDef ParentName="BaseMentalState">
        <defName>MDR_DirectiveBerserker</defName>
        <stateClass>MechHumanlikes.MentalState_DirectiveBerserker</stateClass>
        <label>berserk directives</label>
        <category>Aggro</category>
        <blockRandomInteraction>true</blockRandomInteraction>
        <nameColor>(0.9,0.2,0.5)</nameColor>
        <recoveryMessage>{0}'s berserk directives have terminated.</recoveryMessage>
        <baseInspectLine>Mental state: Berserk directives</baseInspectLine>
        <recoverFromSleep>true</recoverFromSleep>
        <inCaravanCanDo>false</inCaravanCanDo>
        <blocksDefendAndExpandHive>true</blocksDefendAndExpandHive>
  </MentalStateDef>

</Defs>