<?xml version="1.0" encoding="utf-8"?>
<LanguageData>

  <MDR_DirectiveAmicability.stages.0.label>Забавные дроны</MDR_DirectiveAmicability.stages.0.label>
  <MDR_DirectiveAmicability.stages.0.description>Не знаю почему, но я постоянно замечаю, как один из наших дронов делает забавные вещи.</MDR_DirectiveAmicability.stages.0.description>
  <MDR_DirectiveAmicability.stages.1.label>Доброта дрона</MDR_DirectiveAmicability.stages.1.label>
  <MDR_DirectiveAmicability.stages.1.description>Время от времени, дрон делает что-то неожиданно... продуманное? Это приятно.</MDR_DirectiveAmicability.stages.1.description>
  <MDR_DirectiveAmicability.stages.2.label>Дружелюбие дронов</MDR_DirectiveAmicability.stages.2.label>
  <MDR_DirectiveAmicability.stages.2.description>У нас довольно много дронов, которые довольно мирные и почти дружелюбны. Это освежает, но я не знаю, насколько нам это вообще нужно.</MDR_DirectiveAmicability.stages.2.description>


</LanguageData>